fldgen/__init__.py
fldgen/fldGen.py
fldgen/main.py
fldgen_3dbiofibr-0.0.3.dist-info/LICENSE
fldgen_3dbiofibr-0.0.3.dist-info/METADATA
fldgen_3dbiofibr-0.0.3.dist-info/WHEEL
fldgen_3dbiofibr-0.0.3.dist-info/top_level.txt
fldgen_3dbiofibr-0.0.3.dist-info/RECORD
