Metadata-Version: 2.1
Name: fldgen-3dbiofibr
Version: 0.0.3
Summary: Fiber length distribution generator for 3DBiofibr
Author: Gavin Kerr
Author-email: gavin.kerr@dal.ca
Classifier: Programming Language :: Python :: 3
Classifier: License :: OSI Approved :: MIT License
Classifier: Operating System :: OS Independent
Requires-Python: >=3.6
License-File: LICENSE
